osmthedistance/__init__.py
osmthedistance/db.py
osmthedistance/extractors.py
osmthedistance/parsetargets.py
osmthedistance/wayfilters.py
osmthedistance-0.2.0.dist-info/LICENSE
osmthedistance-0.2.0.dist-info/METADATA
osmthedistance-0.2.0.dist-info/WHEEL
osmthedistance-0.2.0.dist-info/top_level.txt
osmthedistance-0.2.0.dist-info/RECORD
